AnChinSegmenter/__init__.py
AnChinSegmenter/evaluate.py
AnChinSegmenter/evaluation.py
AnChinSegmenter/langconv.py
AnChinSegmenter/seg_eval.py
AnChinSegmenter/segmenter.py
AnChinSegmenter/setup.py
AnChinSegmenter/smseg_eval.py
AnChinSegmenter/smseg_helper.py
AnChinSegmenter/smseg_model.py
AnChinSegmenter/smseg_model_curriculum.py
AnChinSegmenter/superloss.py
AnChinSegmenter/test.py
AnChinSegmenter/transformer.py
AnChinSegmenter/use_curriculum.py
AnChinSegmenter/utils.py
AnChinSegmenter/variables.py
AnChinSegmenter/zh_wiki.py
AnChinSegmenter/data/__init__.py
AnChinSegmenter/data/data.py
AnChinSegmenter/data/sample_data.txt
AnChinSegmenter/data/test.txt
AnChinSegmenter/logs/__init__.py
AnChinSegmenter/model/CWS_result.txt
AnChinSegmenter/model/JGW_voc.txt
AnChinSegmenter/model/MSR_voc.txt
AnChinSegmenter/model/SGW_voc.txt
AnChinSegmenter/model/ZGW_voc.txt
AnChinSegmenter/model/__init__.py
AnChinSegmenter/model/dev_metrics.tsv
AnChinSegmenter/model/history.json
AnChinSegmenter/model/test_metrics.tsv
AnChinSegmenter/model/test_result.txt
AnChinSegmenter/pytorch_pretrained_bert/__init__.py
AnChinSegmenter/pytorch_pretrained_bert/__main__.py
AnChinSegmenter/pytorch_pretrained_bert/convert_gpt2_checkpoint_to_pytorch.py
AnChinSegmenter/pytorch_pretrained_bert/convert_openai_checkpoint_to_pytorch.py
AnChinSegmenter/pytorch_pretrained_bert/convert_tf_checkpoint_to_pytorch.py
AnChinSegmenter/pytorch_pretrained_bert/convert_transfo_xl_checkpoint_to_pytorch.py
AnChinSegmenter/pytorch_pretrained_bert/crf.py
AnChinSegmenter/pytorch_pretrained_bert/crf2.py
AnChinSegmenter/pytorch_pretrained_bert/file_utils.py
AnChinSegmenter/pytorch_pretrained_bert/modeling.py
AnChinSegmenter/pytorch_pretrained_bert/modeling_convert.py
AnChinSegmenter/pytorch_pretrained_bert/modeling_gpt2.py
AnChinSegmenter/pytorch_pretrained_bert/modeling_openai.py
AnChinSegmenter/pytorch_pretrained_bert/modeling_transfo_xl.py
AnChinSegmenter/pytorch_pretrained_bert/modeling_transfo_xl_utilities.py
anchinsegmenter-1.0.dist-info/METADATA
anchinsegmenter-1.0.dist-info/WHEEL
anchinsegmenter-1.0.dist-info/entry_points.txt
anchinsegmenter-1.0.dist-info/top_level.txt
anchinsegmenter-1.0.dist-info/RECORD
